elopy/__init__.py
elopy/elo.py
elopy-0.1.3.dist-info/WHEEL
elopy-0.1.3.dist-info/METADATA
elopy-0.1.3.dist-info/RECORD
