Metadata-Version: 2.1
Name: elopy
Version: 0.1.3
Summary: A package to simplify Elo calculations
Home-page: https://github.com/mcbarlowe/elopy
License: MIT
Keywords: elo,sports,basketball,nba
Author: Matt Barlowe
Author-email: mcbarlowe@gmail.com
Requires-Python: >=3.6,<4.0
Classifier: License :: OSI Approved :: MIT License
Classifier: Programming Language :: Python :: 3
Classifier: Programming Language :: Python :: 3.6
Classifier: Programming Language :: Python :: 3.7
Classifier: Programming Language :: Python :: 3.8
Classifier: Programming Language :: Python :: 3.9
Project-URL: Repository, https://github.com/mcbarlowe/elopy
